taskpanel/__init__.py
taskpanel/cli.py
taskpanel/model.py
taskpanel/runner.py
taskpanel/view.py
taskpanel-1.0.2.dist-info/LICENSE
taskpanel-1.0.2.dist-info/METADATA
taskpanel-1.0.2.dist-info/WHEEL
taskpanel-1.0.2.dist-info/entry_points.txt
taskpanel-1.0.2.dist-info/top_level.txt
taskpanel-1.0.2.dist-info/RECORD
