Metadata-Version: 2.1
Name: taskpanel
Version: 1.0.2
Summary: A Robust Interactive Terminal Task Runner Library
Home-page: https://github.com/Wenutu/TaskPanel
Author: Wenutu
Author-email: 
License: UNKNOWN
Project-URL: Bug Reports, https://github.com/Wenutu/TaskPanel/issues
Project-URL: Source, https://github.com/Wenutu/TaskPanel
Project-URL: Documentation, https://github.com/Wenutu/TaskPanel#readme
Keywords: terminal task runner workflow parallel execution curses tui
Platform: UNKNOWN
Classifier: Development Status :: 4 - Beta
Classifier: Intended Audience :: Developers
Classifier: Topic :: Software Development :: Libraries :: Python Modules
Classifier: Topic :: System :: Systems Administration
Classifier: Topic :: Terminals
Classifier: License :: OSI Approved :: MIT License
Classifier: Programming Language :: Python :: 3
Classifier: Programming Language :: Python :: 3.6
Classifier: Programming Language :: Python :: 3.7
Classifier: Programming Language :: Python :: 3.8
Classifier: Programming Language :: Python :: 3.9
Classifier: Programming Language :: Python :: 3.10
Classifier: Programming Language :: Python :: 3.11
Classifier: Programming Language :: Python :: 3.12
Classifier: Operating System :: POSIX
Classifier: Operating System :: MacOS
Classifier: Operating System :: Unix
Classifier: Environment :: Console :: Curses
Requires-Python: >=3.6
License-File: LICENSE
Provides-Extra: dev
Requires-Dist: pytest (>=6.0) ; extra == 'dev'
Requires-Dist: pytest-cov ; extra == 'dev'
Requires-Dist: black ; extra == 'dev'
Requires-Dist: flake8 ; extra == 'dev'
